LICENCE
MANIFEST.in
README.md
setup.cfg
setup.py
Pylowdb.egg-info/PKG-INFO
Pylowdb.egg-info/SOURCES.txt
Pylowdb.egg-info/dependency_links.txt
Pylowdb.egg-info/requires.txt
Pylowdb.egg-info/top_level.txt
Pylowdb.egg-info/zip-safe
pylowdb/__init__.py
pylowdb/adapters.py
pylowdb/errors.py
pylowdb/low.py
tests/__init__.py
tests/test_adapters.py
tests/test_low.py