Metadata-Version: 2.1
Name: Pylowdb
Version: 1.0.2
Summary: Tiny local JSON database for Python, django, flask
Home-page: https://github.com/Ho011/pylowdb
Author: Hussein Sarea
Author-email: zzzsssx0@gmail.com
License: MIT
Project-URL: Bug Reports, https://github.com/Ho011/pylowdb/issues
Project-URL: Funding, https://www.buymeacoffee.com/HusseinSarea
Project-URL: Source, https://github.com/Ho011/pylowdb
Keywords: database,db,electron,embed,embedded,flat,JSON,local,localStorage
Platform: UNKNOWN
Classifier: Development Status :: 5 - Production/Stable
Classifier: Intended Audience :: Developers
Classifier: Intended Audience :: System Administrators
Classifier: License :: OSI Approved :: MIT License
Classifier: Topic :: Database
Classifier: Topic :: Database :: Database Engines/Servers
Classifier: Topic :: Utilities
Classifier: Programming Language :: Python :: 2
Classifier: Programming Language :: Python :: 2.7
Classifier: Programming Language :: Python :: 3
Classifier: Programming Language :: Python :: 3.3
Classifier: Programming Language :: Python :: 3.4
Classifier: Programming Language :: Python :: 3.5
Classifier: Programming Language :: Python :: 3.6
Classifier: Programming Language :: Python :: Implementation :: CPython
Classifier: Programming Language :: Python :: Implementation :: PyPy
Classifier: Operating System :: OS Independent
Requires-Python: >=3.5
License-File: LICENCE
